ccmaps/__init__.py
ccmaps/ccmaps.py
ccmaps/py.typed
ccmaps-0.2.1.dist-info/licenses/LICENSE
ccmaps-0.2.1.dist-info/METADATA
ccmaps-0.2.1.dist-info/WHEEL
ccmaps-0.2.1.dist-info/top_level.txt
ccmaps-0.2.1.dist-info/RECORD
